meddlr_viz/__init__.py
meddlr_viz/utils.py
meddlr_viz/gui/__init__.py
meddlr_viz/gui/perturbation.py
meddlr_viz-0.0.2.dist-info/METADATA
meddlr_viz-0.0.2.dist-info/WHEEL
meddlr_viz-0.0.2.dist-info/top_level.txt
meddlr_viz-0.0.2.dist-info/RECORD
