Metadata-Version: 2.1
Name: meddlr-viz
Version: 0.0.2
Summary: Interfaces for the Meddlr library built with Meerkat.
Home-page: https://github.com/ad12/meddlr_viz
Author: The Meddlr Team
Author-email: arjundd@stanford.edu
Classifier: Programming Language :: Python :: 3
Classifier: Operating System :: OS Independent
Classifier: Topic :: Scientific/Engineering :: Artificial Intelligence
Requires-Python: >=3.6
Requires-Dist: meddlr
Requires-Dist: meerkat-ml
Provides-Extra: all
Requires-Dist: meddlr[dev,docs] ; extra == 'all'
Provides-Extra: dev
Requires-Dist: meddlr[dev,docs] ; extra == 'dev'
